{"background":"map3","music":"elevatorMusic","pieces":[{"type":"indestructible","x":"100","y":"20"},{"type":"indestructible","x":"660","y":"20"},{"type":"indestructible","x":"660","y":"60"},{"type":"indestructible","x":"100","y":"60"},{"type":"indestructible","x":"100","y":"580"},{"type":"indestructible","x":"100","y":"540"},{"type":"indestructible","x":"660","y":"580"},{"type":"indestructible","x":"660","y":"540"},{"type":"indestructible","x":"660","y":"500"},{"type":"indestructible","x":"100","y":"500"},{"type":"indestructible","x":"100","y":"100"},{"type":"indestructible","x":"660","y":"100"},{"type":"wall","x":"780","y":"300"},{"type":"wall","x":"740","y":"300"},{"type":"wall","x":"700","y":"300"},{"type":"wall","x":"660","y":"300"},{"type":"wall","x":"620","y":"300"},{"type":"wall","x":"580","y":"300"},{"type":"wall","x":"540","y":"300"},{"type":"wall","x":"20","y":"300"},{"type":"wall","x":"60","y":"300"},{"type":"wall","x":"100","y":"300"},{"type":"wall","x":"140","y":"300"},{"type":"wall","x":"180","y":"300"},{"type":"wall","x":"220","y":"300"},{"type":"wall","x":"260","y":"300"},{"type":"wall","x":"540","y":"340"},{"type":"wall","x":"540","y":"380"},{"type":"wall","x":"540","y":"260"},{"type":"wall","x":"540","y":"220"},{"type":"wall","x":"260","y":"260"},{"type":"wall","x":"260","y":"220"},{"type":"wall","x":"260","y":"340"},{"type":"wall","x":"260","y":"380"},{"type":"speedPatch","x":"330","y":"270"},{"type":"speedPatch","x":"390","y":"270"},{"type":"speedPatch","x":"450","y":"270"},{"type":"speedPatch","x":"450","y":"330"},{"type":"speedPatch","x":"390","y":"330"},{"type":"speedPatch","x":"330","y":"330"},{"type":"speedPatch","x":"390","y":"210"},{"type":"speedPatch","x":"390","y":"390"},{"type":"healingBeacon","x":"392","y":"296"},{"type":"tnt","x":"516","y":"156"},{"type":"tnt","x":"276","y":"156"},{"type":"tnt","x":"276","y":"444"},{"type":"tnt","x":"516","y":"444"},{"type":"tree","x":"510","y":"30"},{"type":"tree","x":"290","y":"30"},{"type":"tree","x":"510","y":"570"},{"type":"tree","x":"290","y":"570"},{"type":"tree","x":"650","y":"230"},{"type":"tree","x":"650","y":"370"},{"type":"tree","x":"150","y":"370"},{"type":"tree","x":"150","y":"230"}],"players":[{"x":"24","y":"24"},{"x":"744","y":"24"},{"x":"744","y":"552"},{"x":"24","y":"552"}]}
